tact/__init__.py
tact/cli_add_taxa.py
tact/cli_add_toml.py
tact/cli_check_trees.py
tact/cli_taxonomy.py
tact/exceptions.py
tact/fastmrca.py
tact/generic_monophyly.py
tact/lib.py
tact/tree_util.py
tact/validation.py
tact-0.8.0.dist-info/METADATA
tact-0.8.0.dist-info/WHEEL
tact-0.8.0.dist-info/entry_points.txt
tact-0.8.0.dist-info/licenses/LICENSE
tact-0.8.0.dist-info/RECORD
