Metadata-Version: 2.4
Name: tact
Version: 0.8.0
Summary: Taxonomic addition for complete trees: Adds tips to a backbone phylogeny using taxonomy simulated with birth-death models
License-Expression: MIT
License-File: LICENSE
Author: Jonathan Chang
Author-email: me@jonathanchang.org
Maintainer: Jonathan Chang
Maintainer-email: me@jonathanchang.org
Requires-Python: >=3.11,<4
Classifier: Development Status :: 5 - Production/Stable
Classifier: Environment :: Console
Classifier: Intended Audience :: Science/Research
Classifier: Programming Language :: Python :: 3
Classifier: Programming Language :: Python :: 3.11
Classifier: Programming Language :: Python :: 3.12
Classifier: Programming Language :: Python :: 3.13
Classifier: Programming Language :: Python :: 3.14
Classifier: Topic :: Scientific/Engineering :: Bio-Informatics
Provides-Extra: dev
Requires-Dist: DendroPy (>=4.5,<6.0)
Requires-Dist: click (>=8.3.1,<9.0.0)
Requires-Dist: hypothesis (>=6.148.0,<7.0.0) ; extra == "dev"
Requires-Dist: mkdocs ; extra == "dev"
Requires-Dist: mkdocs-git-revision-date-localized-plugin ; extra == "dev"
Requires-Dist: mkdocs-material ; extra == "dev"
Requires-Dist: mkdocstrings ; extra == "dev"
Requires-Dist: mkdocstrings-python ; extra == "dev"
Requires-Dist: mypy (>=1.13.0,<2.0.0) ; extra == "dev"
Requires-Dist: numpy (>=2.3.5,<3.0.0)
Requires-Dist: portion (>=2.2)
Requires-Dist: pytest (>=9.0.1,<10.0.0) ; extra == "dev"
Requires-Dist: pytest-benchmark (>=5.2.3,<6.0.0) ; extra == "dev"
Requires-Dist: pytest-console-scripts (>=1.4.1,<2.0.0) ; extra == "dev"
Requires-Dist: pytest-cov (>=7.0.0,<8.0.0) ; extra == "dev"
Requires-Dist: scipy (>=1.13)
Requires-Dist: toml (>=0.10)
Requires-Dist: types-toml ; extra == "dev"
Project-URL: Documentation, https://tact.jonathanchang.org
Project-URL: Homepage, https://tact.jonathanchang.org
Project-URL: Repository, https://github.com/jonchang/tact
Project-URL: changelog, https://tact.jonathanchang.org/news/
Project-URL: issue, https://github.com/jonchang/tact/issues
Project-URL: sponsor, https://github.com/sponsors/jonchang
